luminet/__init__.py
luminet/black_hole.py
luminet/black_hole_math.py
luminet/isoradial.py
luminet/isoredshift.py
luminet/photon.py
luminet/solver.py
luminet/spatial.py
luminet/viz.py
luminet-0.2.3.dist-info/METADATA
luminet-0.2.3.dist-info/WHEEL
luminet-0.2.3.dist-info/licenses/LICENSE.md
luminet-0.2.3.dist-info/RECORD
