Metadata-Version: 2.4
Name: luminet
Version: 0.2.3
Summary: A leightweight Python package for calculating and plotting Swarzschild black holes with thin accretion disk.
Project-URL: Homepage, https://luminet.readthedocs.io/en/latest/
Project-URL: Documentation, https://luminet.readthedocs.io/en/latest/
Project-URL: Bug Reports, https://github.com/bgmeulem/luminet/issues/new
Project-URL: Source, https://github.com/bgmeulem/luminet
Author-email: bgmeulem <bjorge.meulemeester@mpinb.mpg.de>
License: MIT
License-File: LICENSE.md
Classifier: Development Status :: 4 - Beta
Classifier: Intended Audience :: Education
Classifier: License :: OSI Approved :: MIT License
Classifier: Programming Language :: Python :: 3 :: Only
Classifier: Topic :: Scientific/Engineering :: Astronomy
Classifier: Topic :: Scientific/Engineering :: Physics
Classifier: Topic :: Scientific/Engineering :: Visualization
Requires-Python: >=3.5
